MANIFEST.in
README.md
requirements.txt
setup.py
SSHKeyDistribut0r/__init__.py
SSHKeyDistribut0r/command_line.py
SSHKeyDistribut0r/key_distribut0r.py
SSHKeyDistribut0r.egg-info/PKG-INFO
SSHKeyDistribut0r.egg-info/SOURCES.txt
SSHKeyDistribut0r.egg-info/dependency_links.txt
SSHKeyDistribut0r.egg-info/entry_points.txt
SSHKeyDistribut0r.egg-info/requires.txt
SSHKeyDistribut0r.egg-info/top_level.txt
config/keys.sample.yml
config/servers.sample.yml