Metadata-Version: 1.1
Name: SSHKeyDistribut0r
Version: 0.1.2
Summary: A tool which has been written to make SSH key distribution easier for sysop teams.
Home-page: https://github.com/thomai/SSHKeyDistribut0r
Author: Thomas Maier
Author-email: info@wurps.de
License: CC BY
Keywords: ssh key distribution
Platform: UNKNOWN
Classifier: Development Status :: 5 - Production/Stable
Classifier: Intended Audience :: Developers
Classifier: Intended Audience :: System Administrators
Classifier: Programming Language :: Python
Classifier: Programming Language :: Python :: 2
Classifier: Programming Language :: Python :: 2.7
Classifier: Programming Language :: Python
Classifier: Operating System :: OS Independent
Classifier: Topic :: Communications :: File Sharing
Classifier: Topic :: Security
Classifier: Topic :: Security :: Cryptography
Classifier: Topic :: System :: Networking
Classifier: Topic :: System :: Operating System
Classifier: Topic :: System :: Shells
Classifier: Topic :: System :: Systems Administration
Classifier: Topic :: System :: Systems Administration :: Authentication/Directory
Classifier: Topic :: System :: System Shells
Classifier: Topic :: Terminals
Classifier: Topic :: Utilities
